media_server_client/__init__.py
media_server_client/media_server_client.cpython-312-aarch64-linux-gnu.so
newbringer_network_client-0.1.17.dist-info/METADATA
newbringer_network_client-0.1.17.dist-info/WHEEL
newbringer_network_client-0.1.17.dist-info/RECORD
